rx_data/__init__.py
rx_data/brem_bias_corrector.py
rx_data/electron_bias_corrector.py
rx_data/hop_calculator.py
rx_data/mass_bias_corrector.py
rx_data/mis_calculator.py
rx_data/mva_calculator.py
rx_data/path_splitter.py
rx_data/rdf_getter.py
rx_data/rdf_getter12.py
rx_data/stats.py
rx_data/swp_calculator.py
rx_data/utilities.py
rx_data_data/__init__.py
rx_data_data/copy_files/README.md
rx_data_data/copy_files/rk.yaml
rx_data_data/friend_trees/nopid.yaml
rx_data_data/rdf_getter/config.yaml
rx_data_data/rdf_getter/triggers.yaml
rx_data_data/rdf_getter12/config.yaml
rx_data_data/tests/mass_bias_corrector/mass_overlay.yaml
rx_data_data/tests/rdf_getter/config.yaml
rx_data_data/tests/swap_adder/bpd0kpienu.json
rx_data_lfns/__init__.py
rx_data_lfns/lbpkmumu/README.md
rx_data_lfns/lbpkmumu/v1/lfn_104.json
rx_data_lfns/lbpkmumu/v1/lfn_105.json
rx_data_lfns/lbpkmumu/v1/lfn_106.json
rx_data_lfns/lbpkmumu/v1/lfn_107.json
rx_data_lfns/lbpkmumu/v1/lfn_108.json
rx_data_lfns/lbpkmumu/v1/lfn_109.json
rx_data_lfns/lbpkmumu/v1/lfn_110.json
rx_data_lfns/lbpkmumu/v1/lfn_111.json
rx_data_lfns/nopid/README.md
rx_data_lfns/nopid/v1/lfn_335.json
rx_data_lfns/nopid/v1/lfn_336.json
rx_data_lfns/nopid/v1/lfn_337.json
rx_data_lfns/nopid/v1/lfn_338.json
rx_data_lfns/nopid/v1/lfn_340.json
rx_data_lfns/nopid/v1/lfn_341.json
rx_data_lfns/nopid/v1/lfn_342.json
rx_data_lfns/nopid/v1/lfn_343.json
rx_data_lfns/nopid/v1/lfn_344.json
rx_data_lfns/nopid/v1/lfn_345.json
rx_data_lfns/nopid/v1/lfn_346.json
rx_data_lfns/nopid/v1/lfn_347.json
rx_data_lfns/rx/v1/README.md
rx_data_lfns/rx/v1/lfn_047.json
rx_data_lfns/rx/v1/lfn_048.json
rx_data_lfns/rx/v1/lfn_049.json
rx_data_lfns/rx/v1/lfn_050.json
rx_data_lfns/rx/v10/README.md
rx_data_lfns/rx/v10/lfn_247.json
rx_data_lfns/rx/v10/lfn_248.json
rx_data_lfns/rx/v10/lfn_249.json
rx_data_lfns/rx/v10/lfn_250.json
rx_data_lfns/rx/v10/lfn_251.json
rx_data_lfns/rx/v10/lfn_252.json
rx_data_lfns/rx/v10/lfn_253.json
rx_data_lfns/rx/v10/lfn_254.json
rx_data-0.2.1.dist-info/METADATA
rx_data-0.2.1.dist-info/WHEEL
rx_data-0.2.1.dist-info/entry_points.txt
rx_data-0.2.1.dist-info/RECORD
