Metadata-Version: 2.3
Name: rx_data
Version: 0.2.1
Summary: Project with lists of LFNs and utilities needed to download filteres ntuples
Requires-Python: >=3.10,<3.13
Classifier: Programming Language :: Python :: 3
Classifier: Programming Language :: Python :: 3.10
Classifier: Programming Language :: Python :: 3.11
Classifier: Programming Language :: Python :: 3.12
Provides-Extra: ci
Provides-Extra: net
Provides-Extra: tst
Requires-Dist: ap_utilities (>=0.0.0)
Requires-Dist: data-manipulation-utilities (>=0.0.0)
Requires-Dist: ecal_calibration (>=0.0.0) ; extra == "ci"
Requires-Dist: mplhep (>=0.0.0)
Requires-Dist: pandarallel (>=0.0.0)
Requires-Dist: particle (>=0.0.0)
Requires-Dist: prefect (>=3.4.9,<4.0.0)
Requires-Dist: pytest (>=0.0.0) ; extra == "tst"
Requires-Dist: tabulate (>=0.0.0)
Requires-Dist: tqdm (>=0.0.0)
Requires-Dist: uproot (>=0.0.0)
Requires-Dist: vector (>=0.0.0)
Requires-Dist: xrootd (>=0.0.0) ; extra == "net"
